latexSAK.py
latexsak-0.2.4.dist-info/licenses/LICENSE
latexsak-0.2.4.dist-info/METADATA
latexsak-0.2.4.dist-info/WHEEL
latexsak-0.2.4.dist-info/entry_points.txt
latexsak-0.2.4.dist-info/top_level.txt
latexsak-0.2.4.dist-info/RECORD
