Metadata-Version: 2.4
Name: latexSAK
Version: 0.2.4
Summary: Swiss army knife for LaTeX files.
Author-email: Géry Casiez <gery.casiez@gmail.com>
License-Expression: MIT
Project-URL: Homepage, https://github.com/casiez/latexSAK
Classifier: Programming Language :: Python :: 3
Classifier: Operating System :: MacOS
Classifier: Operating System :: POSIX :: Linux
Requires-Python: >=3.0
License-File: LICENSE
Requires-Dist: argparse
Requires-Dist: texsoup
Dynamic: license-file
